pollax/__init__.py
pollax/client.py
pollax/errors.py
pollax/models.py
pollax/resources/__init__.py
pollax/resources/agents.py
pollax/resources/analytics.py
pollax/resources/api_keys.py
pollax/resources/calls.py
pollax/resources/campaigns.py
pollax/resources/integrations.py
pollax/resources/knowledge.py
pollax/resources/phone_numbers.py
pollax/resources/voice_cloning.py
pollax-1.0.0.dist-info/METADATA
pollax-1.0.0.dist-info/WHEEL
pollax-1.0.0.dist-info/top_level.txt
pollax-1.0.0.dist-info/RECORD
