Metadata-Version: 2.4
Name: pollax
Version: 1.0.0
Summary: Official Python SDK for the Pollax AI Voice Platform
Author-email: Pollax <support@pollax.ai>
License: MIT
Project-URL: Homepage, https://pollax.ai
Project-URL: Documentation, https://docs.pollax.ai
Project-URL: Repository, https://github.com/pollax/pollax-python
Project-URL: Bug Tracker, https://github.com/pollax/pollax-python/issues
Keywords: pollax,ai,voice,calling,telephony,speech
Classifier: Development Status :: 5 - Production/Stable
Classifier: Intended Audience :: Developers
Classifier: License :: OSI Approved :: MIT License
Classifier: Programming Language :: Python :: 3
Classifier: Programming Language :: Python :: 3.8
Classifier: Programming Language :: Python :: 3.9
Classifier: Programming Language :: Python :: 3.10
Classifier: Programming Language :: Python :: 3.11
Classifier: Programming Language :: Python :: 3.12
Classifier: Topic :: Software Development :: Libraries :: Python Modules
Requires-Python: >=3.8
Requires-Dist: httpx>=0.24.0
Requires-Dist: pydantic>=2.0.0
Requires-Dist: typing-extensions>=4.0.0
Provides-Extra: dev
Requires-Dist: pytest>=7.0.0; extra == "dev"
Requires-Dist: pytest-asyncio>=0.21.0; extra == "dev"
Requires-Dist: black>=23.0.0; extra == "dev"
Requires-Dist: mypy>=1.0.0; extra == "dev"
Requires-Dist: ruff>=0.0.270; extra == "dev"
